{
    "character": {
        "summary": {
            "name": "Jaina",
            "fullName": "Jaina Stormborne",
            "title": "Phoenix Archer",
            "hitPoints": 85,
            "maxCombo": 5,
            "attackSpeed": 6,
            "throwSpeed": 6,
            "throwDamage": 7,
            "attacks": [2, 3, 4, 5, 6, "J", "Q", "K", "A"],
            "throws": [6, 7, 8, 9, "T"],
            "blocks": [7, 8, 9, "T"],
            "dodges": [2, 3, 4, 5],
            "innateAbilities": [
                {
                    "name": "Burning Vigor",
                    "text": "At the end of combat, if you attacked, you may return any number of combo cards to your hand other than Queens or Aces. Take 3 damage for each card returned this way."
                },
                {
                    "name": "Burning Desperation",
                    "text": "If you have 35 life or less, you may also return Queens and Aces and take 4 damage for each."
                }
            ],
            "cardAbilities": [
                {
                    "rank": 7,
                    "name": "Unstable Power",
                    "timing": "Draw Phase",
                    "text": "Knocked down opponents stand up. You can't play Aces this turn, but you can rotate your combat-revealed attack 180 degrees. If you hit the opponent this combat, search your deck or discard pile for 2 Aces. Otherwise, take 7 damage."
                },
                {
                    "rank": "T",
                    "name": "Smoldering Embers",
                    "timing": "Combat Reveal",
                    "text": "If the opponent dodged while this card is in your discard pile, they take two damage. You can't power up with this card. (It's too hot.)"
                }
            ]
        },
        "attacks": [
            {"rank": 2, "chip": "(1)", "notes": "Chip Damage only on Red"},
            {"rank": 3, "chip": "(2)", "notes": "Chip Damage only on Red"},
            {"rank": 4, "chip": "(3)", "notes": "Chip Damage only on Red"},
            {"rank": 5, "chip": "(4)", "notes": "Chip Damage only on Red"},
            {"rank": 6, "chip": "(5)", "notes": "Chip Damage only on Red"},
            {"speed": 2.6, "rank": "J", "name": "Flame Arrow", "damage": 6, "chip": 5},
            {"speed": 4.6, "rank": "J", "name": "Charged Shot", "damage": 8, "chip": 7},
            {"speed": 0.2, "rank": "Q", "name": "Dragonheart", "pumpWith": "+X", "damage": 8, "pump": 5, "chip": 1},
            {"speed": 2.4, "rank": "K", "name": "Crossfire Kick", "pumpWith": "+K+K+K", "damage": 6, "pump": 7, "chip": 3},
            {"speed": 0.8, "rank": "A", "name": "Red Dragon", "pumpWith": "+A+A+A", "damage": 10, "pump": 9, "chip": 2},
            {"speed": 0.2, "rank": "AA", "name": "Letter J", "damage": 18, "chip": 4}
        ],
        "throws": [
            {"rank": 7},
            {"rank": 8},
            {"rank": 9},
            {"rank": "T"}
        ]
    }
}
